gcm/__init__.py
gcm/gcm.py
version/__init__.py
version/__main__.py
version/lib.py
olve_utilities-0.0.14.post20241219035531.dist-info/METADATA
olve_utilities-0.0.14.post20241219035531.dist-info/WHEEL
olve_utilities-0.0.14.post20241219035531.dist-info/entry_points.txt
olve_utilities-0.0.14.post20241219035531.dist-info/RECORD
