Metadata-Version: 2.4
Name: olve.utilities
Version: 0.0.14.post20241219035531
Summary: Various utility CLI applications
Requires-Python: >=3.12
Requires-Dist: gitpython>=3.1.43
Requires-Dist: typer>=0.15.1
